Metadata-Version: 1.0
Name: distributions-up
Version: 0.1
Summary: Gaussian and Binomial distributions
Home-page: UNKNOWN
Author: Jose Ceron
Author-email: jceronrodriguez10@gmail.com
License: UNKNOWN
Platform: UNKNOWN
